comcigan/__init__.py
comcigan/async_school.py
comcigan/reg.py
comcigan/school.py
comcigan/school_new.py
comcigan-1.4.9.dist-info/LICENSE
comcigan-1.4.9.dist-info/METADATA
comcigan-1.4.9.dist-info/WHEEL
comcigan-1.4.9.dist-info/top_level.txt
comcigan-1.4.9.dist-info/RECORD
