Metadata-Version: 2.1
Name: comcigan
Version: 1.4.9
Summary: Unofficial Comcigan API python wrapper
Home-page: https://github.com/Coder-Iro/comcigan-py
Author: Coder-Iro
Author-email: doohee006@gmail.com
Classifier: Programming Language :: Python :: 3
Classifier: License :: OSI Approved :: GNU Lesser General Public License v3 or later (LGPLv3+)
Classifier: Operating System :: OS Independent
Requires-Python: >=3.7
License-File: LICENSE
Requires-Dist: requests
Requires-Dist: beautifulsoup4
Requires-Dist: aiohttp
Requires-Dist: lxml
